AUTHORS
LICENSE
MANIFEST.in
README.rst
setup.py
django_urlcrypt.egg-info/PKG-INFO
django_urlcrypt.egg-info/SOURCES.txt
django_urlcrypt.egg-info/dependency_links.txt
django_urlcrypt.egg-info/not-zip-safe
django_urlcrypt.egg-info/top_level.txt
urlcrypt/__init__.py
urlcrypt/auth_backends.py
urlcrypt/conf.py
urlcrypt/lib.py
urlcrypt/models.py
urlcrypt/oaep.py
urlcrypt/rsa.py
urlcrypt/tests.py
urlcrypt/urls.py
urlcrypt/views.py
urlcrypt/templatetags/__init__.py
urlcrypt/templatetags/urlcrypt_tags.py
urlcrypt/test/test_private_key