Metadata-Version: 1.0
Name: django-urlcrypt
Version: 0.1.6
Summary: Encrypts information in urls, such as login credentials. Useful if you want to send a user a link that logs the user in without leaking their login credentials.
Home-page: http://github.com/dziegler/django-urlcrypt
Author: David Ziegler
Author-email: david.ziegler@gmail.com
License: BSD
Platform: UNKNOWN
Classifier: Environment :: Web Environment
Classifier: Framework :: Django
Classifier: Intended Audience :: Developers
Classifier: License :: OSI Approved :: BSD License
Classifier: Operating System :: OS Independent
Classifier: Programming Language :: Python
Classifier: Topic :: Internet :: WWW/HTTP
